README.md
setup.py
dynamo_size/__init__.py
dynamo_size.egg-info/PKG-INFO
dynamo_size.egg-info/SOURCES.txt
dynamo_size.egg-info/dependency_links.txt
dynamo_size.egg-info/top_level.txt