Metadata-Version: 2.1
Name: dynamo-size
Version: 1.0.1
Summary: Roughly calculates DynamoDB item size.
Home-page: https://github.com/tallesl/py-dynamo-size
Author: Talles Lasmar
Author-email: talleslasmar@gmail.com
License: UNKNOWN
Platform: UNKNOWN
